setup.cfg
setup.py
incapsula/__init__.py
incapsula_cracker_py3.egg-info/PKG-INFO
incapsula_cracker_py3.egg-info/SOURCES.txt
incapsula_cracker_py3.egg-info/dependency_links.txt
incapsula_cracker_py3.egg-info/requires.txt
incapsula_cracker_py3.egg-info/top_level.txt