Metadata-Version: 1.0
Name: incapsula-cracker-py3
Version: 0.1.7
Summary: A way to bypass incapsula robot checks when using requests.
Home-page: https://github.com/ziplokk1/incapsula-cracker-py3
Author: Mark Sanders
Author-email: sdscdeveloper@gmail.com
License: LICENSE.txt
Platform: UNKNOWN
